ignores/__init__.py
ignores-0.0.0.dist-info/LICENSE
ignores-0.0.0.dist-info/METADATA
ignores-0.0.0.dist-info/WHEEL
ignores-0.0.0.dist-info/top_level.txt
ignores-0.0.0.dist-info/RECORD
